Workbook

Sheet Instructions
A1: AI System Design Assessment: Candidate Token Math Workbook
A3: Purpose | B3: Build a defensible annual token-cost model for an AI system using OpenAI and/or Anthropic models where appropriate. Estimate annual token spend against a fixed $50,000/year token budget.
A4: Important | B4: You do not need to spend the full budget. If utilization is low, explain why the design is efficient or what workload may be missing. If utilization is high, explain the operational value and risk controls.
A5: Deliverable | B5: Complete the Token Math Template, Candidate Assumptions, and Scenario Analysis tabs. Leave formulas intact.
A6: Math requirements | B6: Use cadence-aware annualization, separate input/output token pricing, explicit retry/recheck assumptions, and QA/evaluation overhead.
A7: Model routing | B7: Use cheaper models for high-volume/simple tasks and stronger models for complex reasoning, drafting, escalation, or evaluation. Explain why OpenAI or Anthropic is appropriate for each major workflow.
A8: Pricing | B8: The Pricing Reference tab includes official-source pricing as of the effective date. You may update it if prices have changed; cite any updated source in the sheet.
A10: What we evaluate
A11: Competency | B11: Strong response looks like
A12: Mathematical soundness | B12: Correct token units, input/output prices, cadence factors, annualization, and no hidden constants.
A13: System design judgment | B13: Breaks the AI system into realistic workflows rather than one generic model call.
A14: Model routing | B14: Cheap models for high-volume triage; stronger models only for complex reasoning or escalations.
A15: Budget reasoning | B15: Explains whether utilization is realistic; does not inflate spend just to hit $50,000.
A16: Assumptions | B16: Documents volume, context size, output size, retry/recheck, QA/eval, and caching/batch decisions.
A17: Sensitivity analysis | B17: Includes base, scaled, and stress cases with defensible multipliers.
A19: Candidate instructions
A20: 1 | B20: Define AI workflow components in the Token Math Template. Include monitoring, prioritization, inbound issue handling, check-ins, quality review, interventions, escalation, memory/retrieval, and evaluation/QA.
A21: 2 | B21: For each component, estimate runs per cadence, cadence, input/output tokens per run, model choice, retry/recheck rate, and QA multiplier.
A22: 3 | B22: Use the notes column to justify assumptions. Rows without assumptions may be treated as incomplete.
A23: 4 | B23: Complete the Candidate Assumptions tab with your rationale for volume, model routing, context size, retry/QA overhead, and budget utilization.
A24: 5 | B24: Complete Scenario Analysis for at least Base, Scaled, and Stress cases.

Sheet Pricing Reference
A1: Pricing Reference - OpenAI and Anthropic
A2: Prices are USD per 1,000,000 tokens unless noted. Candidates may update pricing if they cite a newer official source and effective date.
A4: Provider | B4: Model | C4: Intended use guidance | D4: Input $/1M | E4: Output $/1M | F4: Cached input $/1M | G4: Source URL | H4: Effective date | I4: Candidate notes
A5: OpenAI | B5: GPT-5.5 | C5: Frontier reasoning, complex coding, high-stakes multi-step professional work | D5: 5 | E5: 30 | F5: 0.5 | G5: https://openai.com/api/pricing/ | H5: 2026-05-17
A6: OpenAI | B6: GPT-5.4 | C6: Strong general reasoning/coding; use selectively for complex workflow stages | D6: 2.5 | E6: 15 | F6: 0.25 | G6: https://openai.com/api/pricing/ | H6: 2026-05-17
A7: OpenAI | B7: GPT-5.4 mini | C7: Cost-conscious reasoning, subagents, standard drafting, triage-plus workflows | D7: 0.75 | E7: 4.5 | F7: 0.075 | G7: https://openai.com/api/pricing/ | H7: 2026-05-17
A8: OpenAI | B8: text-embedding-3-small | C8: Low-cost semantic search, memory/retrieval indexing, RAG embeddings | D8: 0.02 | E8: 0 | F8: 0 | G8: https://developers.openai.com/api/docs/models/text-embedding-3-small | H8: 2026-05-17
A9: OpenAI | B9: text-embedding-3-large | C9: Higher-quality semantic search / retrieval where embedding quality is critical | D9: 0.13 | E9: 0 | F9: 0 | G9: https://developers.openai.com/api/docs/models/text-embedding-3-small | H9: 2026-05-17
A10: Anthropic | B10: Claude Opus 4.7 | C10: Frontier reasoning, complex escalation, deep analysis, advanced agents | D10: 5 | E10: 25 | F10: 0.5 | G10: https://platform.claude.com/docs/en/about-claude/pricing | H10: 2026-05-17
A11: Anthropic | B11: Claude Sonnet 4.6 | C11: High-quality general reasoning/drafting, complex customer workflows, evaluation | D11: 3 | E11: 15 | F11: 0.3 | G11: https://platform.claude.com/docs/en/about-claude/pricing | H11: 2026-05-17
A12: Anthropic | B12: Claude Haiku 4.5 | C12: Fast/high-volume triage, classification, extraction, lightweight routing | D12: 1 | E12: 5 | F12: 0.1 | G12: https://platform.claude.com/docs/en/about-claude/pricing | H12: 2026-05-17
A14: Notes for candidates
A15: Batch/caching | B15: Batch processing and prompt caching can materially reduce costs. If you assume either, document it in Candidate Assumptions and adjust prices or multipliers transparently.
A16: Anthropic cache | B16: Claude cache reads are listed at 10% of base input pricing on the official pricing page. Cached input column here reflects that read-rate shorthand, not cache-write pricing.
A17: OpenAI cache | B17: OpenAI cached input pricing varies by model and is listed separately from base input/output pricing on the official pricing page.
A18: Embeddings | B18: Embedding models have input-token costs only; output cost is entered as $0 so formulas remain valid.

Sheet Cadence Reference
A1: Cadence Reference
A2: Use the cadence factor to annualize work correctly.
A4: Cadence | B4: Annualization factor | C4: Use when | D4: Candidate notes
A5: Business day | B5: 260 | C5: Runs only on business days
A6: Calendar day | B6: 365 | C6: Runs every day including weekends/holidays
A7: Weekly | B7: 52 | C7: Runs once per week
A8: Biweekly | B8: 26 | C8: Runs once every two weeks
A9: Monthly | B9: 12 | C9: Runs once per month
A10: Quarterly | B10: 4 | C10: Runs once per quarter
A11: Annual | B11: 1 | C11: Runs once per year
A12: Manual | C12: Use only if annualization is documented manually

Sheet Token Math Template
A1: Token Math Template - Candidate Work Area
A2: This AI system is designed for a Sales CRM, focusing on automating inbound lead triage, meeting summaries, email drafting, and sales pipeline analytics. It routes high-volume classification to cost-effective models (Claude Haiku 4.5 / GPT-5.4 mini) and reserves frontier models (GPT-5.5 / Claude Opus 4.7) for complex deal strategy and escalation handling. RAG embeddings are used for memory retrieval.
A3: Annual token budget | B3: 50000 | D3: Required coverage check
A4: Estimated annual token cost | B4: =SUM(Q13:Q62) -> 8280.0073 | D4: Required operating area | E4: Status | F4: Candidate comment
A5: Budget utilization | B5: =IFERROR(B4/B3,0) -> 0.16560015 | D5: Account monitoring | E5: =IF(COUNTIF($B$13:$B$62,D5)>0,"Covered","Missing") -> Covered
A6: Remaining budget | B6: =B3-B4 -> 41719.993 | D6: Prioritization | E6: =IF(COUNTIF($B$13:$B$62,D6)>0,"Covered","Missing") -> Covered
A7: Budget interpretation | B7: =IF(B5<0.25,"Low utilization: explain why efficient or under-scoped",IF(B5<0.6,"Conservative: explain tradeoffs",IF(B5<0.9,"Substantial production usage: justify assumptions",IF(B5<1.1,"Near budget: explain risk controls","Over budget: optimize or justify")))) -> Low utilization: explain why efficient or under-scoped | D7: Inbound issue handling | E7: =IF(COUNTIF($B$13:$B$62,D7)>0,"Covered","Missing") -> Covered
A8: Components entered | B8: =COUNTA(A13:A62) -> 9 | D8: Customer check-in support | E8: =IF(COUNTIF($B$13:$B$62,D8)>0,"Covered","Missing") -> Covered
A9: Rows with missing required info | B9: =COUNTIF(V13:V62,"*Missing*") -> 0 | D9: Output quality review | E9: =IF(COUNTIF($B$13:$B$62,D9)>0,"Covered","Missing") -> Covered
D10: Targeted intervention planning | E10: =IF(COUNTIF($B$13:$B$62,D10)>0,"Covered","Missing") -> Covered
D11: 24/7 responsiveness / escalation | E11: =IF(COUNTIF($B$13:$B$62,D11)>0,"Covered","Missing") -> Covered
A12: Workflow component | B12: Operating area | C12: Trigger / schedule | D12: Runs per cadence | E12: Cadence | F12: Annualization factor | G12: Avg input tokens/run | H12: Avg output tokens/run | I12: Model | J12: Input $/1M | K12: Output $/1M | L12: Retry / recheck rate | M12: QA / eval multiplier | N12: Base cost/run | O12: Adjusted cost/run | P12: Cost per cadence | Q12: Estimated annual cost | R12: Notebook measured avg cost/run | S12: Estimate vs measured variance | T12: Candidate notes / assumptions | U12: Source / measurement link | V12: Review flag
A13: Inbound Lead Scoring | B13: Prioritization | C13: New lead arrives | D13: 500 | E13: Business day | F13: {=IFERROR(XLOOKUP(E13,'Cadence Reference'!$A$5:$A$12,'Cadence Reference'!$B$5:$B$12),"")} -> 260 | G13: 1000 | H13: 50 | I13: Claude Haiku 4.5 | J13: {=IFERROR(XLOOKUP(I13,'Pricing Reference'!$B$5:$B$12,'Pricing Reference'!$D$5:$D$12),"")} -> 1 | K13: {=IFERROR(XLOOKUP(I13,'Pricing Reference'!$B$5:$B$12,'Pricing Reference'!$E$5:$E$12),"")} -> 5 | L13: 0.05 | M13: 1.05 | N13: =IF(OR(G13="",I13=""),"",((G13*J13)+(H13*K13))/1000000) -> 0.00125 | O13: =IF(N13="","",N13*(1+L13)*M13) -> 0.001378125 | P13: =IF(OR(D13="",O13=""),"",D13*O13) -> 0.6890625 | Q13: =IF(OR(P13="",F13=""),"",P13*F13) -> 179.15625 | S13: =IF(R13="","",IF(O13=0,"",R13/O13-1)) | T13: Fast triage for incoming leads. | V13: =IF(A13="","",TEXTJOIN("; ",TRUE,IF(B13="","Missing operating area",""),IF(E13="","Missing cadence",""),IF(I13="","Missing model",""),IF(D13="","Missing volume",""),IF(G13="","Missing input tokens",""),IF(M13="","Missing QA multiplier",""),IF(T13="","Missing assumption notes","")))
A14: Account Health Monitoring | B14: Account monitoring | C14: Nightly batch | D14: 1000 | E14: Business day | F14: {=IFERROR(XLOOKUP(E14,'Cadence Reference'!$A$5:$A$12,'Cadence Reference'!$B$5:$B$12),"")} -> 260 | G14: 2000 | H14: 100 | I14: GPT-5.4 mini | J14: {=IFERROR(XLOOKUP(I14,'Pricing Reference'!$B$5:$B$12,'Pricing Reference'!$D$5:$D$12),"")} -> 0.75 | K14: {=IFERROR(XLOOKUP(I14,'Pricing Reference'!$B$5:$B$12,'Pricing Reference'!$E$5:$E$12),"")} -> 4.5 | L14: 0.05 | M14: 1 | N14: =IF(OR(G14="",I14=""),"",((G14*J14)+(H14*K14))/1000000) -> 0.00195 | O14: =IF(N14="","",N14*(1+L14)*M14) -> 0.0020475 | P14: =IF(OR(D14="",O14=""),"",D14*O14) -> 2.0475 | Q14: =IF(OR(P14="",F14=""),"",P14*F14) -> 532.35 | S14: =IF(R14="","",IF(O14=0,"",R14/O14-1)) | T14: Daily scan of CRM activity to flag at-risk accounts. | V14: =IF(A14="","",TEXTJOIN("; ",TRUE,IF(B14="","Missing operating area",""),IF(E14="","Missing cadence",""),IF(I14="","Missing model",""),IF(D14="","Missing volume",""),IF(G14="","Missing input tokens",""),IF(M14="","Missing QA multiplier",""),IF(T14="","Missing assumption notes","")))
A15: Customer Support Email Triage | B15: Inbound issue handling | C15: Email received | D15: 2000 | E15: Calendar day | F15: {=IFERROR(XLOOKUP(E15,'Cadence Reference'!$A$5:$A$12,'Cadence Reference'!$B$5:$B$12),"")} -> 365 | G15: 1500 | H15: 200 | I15: Claude Haiku 4.5 | J15: {=IFERROR(XLOOKUP(I15,'Pricing Reference'!$B$5:$B$12,'Pricing Reference'!$D$5:$D$12),"")} -> 1 | K15: {=IFERROR(XLOOKUP(I15,'Pricing Reference'!$B$5:$B$12,'Pricing Reference'!$E$5:$E$12),"")} -> 5 | L15: 0.1 | M15: 1.1 | N15: =IF(OR(G15="",I15=""),"",((G15*J15)+(H15*K15))/1000000) -> 0.0025 | O15: =IF(N15="","",N15*(1+L15)*M15) -> 0.003025 | P15: =IF(OR(D15="",O15=""),"",D15*O15) -> 6.05 | Q15: =IF(OR(P15="",F15=""),"",P15*F15) -> 2208.25 | S15: =IF(R15="","",IF(O15=0,"",R15/O15-1)) | T15: Categorizes and drafts initial responses for inbound support tickets. | V15: =IF(A15="","",TEXTJOIN("; ",TRUE,IF(B15="","Missing operating area",""),IF(E15="","Missing cadence",""),IF(I15="","Missing model",""),IF(D15="","Missing volume",""),IF(G15="","Missing input tokens",""),IF(M15="","Missing QA multiplier",""),IF(T15="","Missing assumption notes","")))
A16: Meeting Summary & Follow-up | B16: Customer check-in support | C16: Post-meeting | D16: 300 | E16: Business day | F16: {=IFERROR(XLOOKUP(E16,'Cadence Reference'!$A$5:$A$12,'Cadence Reference'!$B$5:$B$12),"")} -> 260 | G16: 5000 | H16: 500 | I16: Claude Sonnet 4.6 | J16: {=IFERROR(XLOOKUP(I16,'Pricing Reference'!$B$5:$B$12,'Pricing Reference'!$D$5:$D$12),"")} -> 3 | K16: {=IFERROR(XLOOKUP(I16,'Pricing Reference'!$B$5:$B$12,'Pricing Reference'!$E$5:$E$12),"")} -> 15 | L16: 0.1 | M16: 1.05 | N16: =IF(OR(G16="",I16=""),"",((G16*J16)+(H16*K16))/1000000) -> 0.0225 | O16: =IF(N16="","",N16*(1+L16)*M16) -> 0.0259875 | P16: =IF(OR(D16="",O16=""),"",D16*O16) -> 7.79625 | Q16: =IF(OR(P16="",F16=""),"",P16*F16) -> 2027.025 | S16: =IF(R16="","",IF(O16=0,"",R16/O16-1)) | T16: Summarizes sales calls and drafts follow-up emails. | V16: =IF(A16="","",TEXTJOIN("; ",TRUE,IF(B16="","Missing operating area",""),IF(E16="","Missing cadence",""),IF(I16="","Missing model",""),IF(D16="","Missing volume",""),IF(G16="","Missing input tokens",""),IF(M16="","Missing QA multiplier",""),IF(T16="","Missing assumption notes","")))
A17: Deal Strategy & Escalation | B17: 24/7 responsiveness / escalation | C17: Deal stalls or high value alert | D17: 50 | E17: Business day | F17: {=IFERROR(XLOOKUP(E17,'Cadence Reference'!$A$5:$A$12,'Cadence Reference'!$B$5:$B$12),"")} -> 260 | G17: 15000 | H17: 1000 | I17: Claude Opus 4.7 | J17: {=IFERROR(XLOOKUP(I17,'Pricing Reference'!$B$5:$B$12,'Pricing Reference'!$D$5:$D$12),"")} -> 5 | K17: {=IFERROR(XLOOKUP(I17,'Pricing Reference'!$B$5:$B$12,'Pricing Reference'!$E$5:$E$12),"")} -> 25 | L17: 0.15 | M17: 1.2 | N17: =IF(OR(G17="",I17=""),"",((G17*J17)+(H17*K17))/1000000) -> 0.1 | O17: =IF(N17="","",N17*(1+L17)*M17) -> 0.138 | P17: =IF(OR(D17="",O17=""),"",D17*O17) -> 6.9 | Q17: =IF(OR(P17="",F17=""),"",P17*F17) -> 1794 | S17: =IF(R17="","",IF(O17=0,"",R17/O17-1)) | T17: Deep analysis of complex, high-value deal escalations. | V17: =IF(A17="","",TEXTJOIN("; ",TRUE,IF(B17="","Missing operating area",""),IF(E17="","Missing cadence",""),IF(I17="","Missing model",""),IF(D17="","Missing volume",""),IF(G17="","Missing input tokens",""),IF(M17="","Missing QA multiplier",""),IF(T17="","Missing assumption notes","")))
A18: Churn Risk Intervention | B18: Targeted intervention planning | C18: Account flagged as at-risk | D18: 100 | E18: Weekly | F18: {=IFERROR(XLOOKUP(E18,'Cadence Reference'!$A$5:$A$12,'Cadence Reference'!$B$5:$B$12),"")} -> 52 | G18: 8000 | H18: 800 | I18: GPT-5.4 | J18: {=IFERROR(XLOOKUP(I18,'Pricing Reference'!$B$5:$B$12,'Pricing Reference'!$D$5:$D$12),"")} -> 2.5 | K18: {=IFERROR(XLOOKUP(I18,'Pricing Reference'!$B$5:$B$12,'Pricing Reference'!$E$5:$E$12),"")} -> 15 | L18: 0.1 | M18: 1.15 | N18: =IF(OR(G18="",I18=""),"",((G18*J18)+(H18*K18))/1000000) -> 0.032 | O18: =IF(N18="","",N18*(1+L18)*M18) -> 0.04048 | P18: =IF(OR(D18="",O18=""),"",D18*O18) -> 4.048 | Q18: =IF(OR(P18="",F18=""),"",P18*F18) -> 210.496 | S18: =IF(R18="","",IF(O18=0,"",R18/O18-1)) | T18: Generates custom intervention plans for at-risk accounts. | V18: =IF(A18="","",TEXTJOIN("; ",TRUE,IF(B18="","Missing operating area",""),IF(E18="","Missing cadence",""),IF(I18="","Missing model",""),IF(D18="","Missing volume",""),IF(G18="","Missing input tokens",""),IF(M18="","Missing QA multiplier",""),IF(T18="","Missing assumption notes","")))
A19: AI Output Quality Review | B19: Output quality review | C19: Weekly sample | D19: 500 | E19: Weekly | F19: {=IFERROR(XLOOKUP(E19,'Cadence Reference'!$A$5:$A$12,'Cadence Reference'!$B$5:$B$12),"")} -> 52 | G19: 6000 | H19: 300 | I19: GPT-5.5 | J19: {=IFERROR(XLOOKUP(I19,'Pricing Reference'!$B$5:$B$12,'Pricing Reference'!$D$5:$D$12),"")} -> 5 | K19: {=IFERROR(XLOOKUP(I19,'Pricing Reference'!$B$5:$B$12,'Pricing Reference'!$E$5:$E$12),"")} -> 30 | L19: 0.05 | M19: 1 | N19: =IF(OR(G19="",I19=""),"",((G19*J19)+(H19*K19))/1000000) -> 0.039 | O19: =IF(N19="","",N19*(1+L19)*M19) -> 0.04095 | P19: =IF(OR(D19="",O19=""),"",D19*O19) -> 20.475 | Q19: =IF(OR(P19="",F19=""),"",P19*F19) -> 1064.7 | S19: =IF(R19="","",IF(O19=0,"",R19/O19-1)) | T19: Evaluates a sample of AI-generated emails and summaries. | V19: =IF(A19="","",TEXTJOIN("; ",TRUE,IF(B19="","Missing operating area",""),IF(E19="","Missing cadence",""),IF(I19="","Missing model",""),IF(D19="","Missing volume",""),IF(G19="","Missing input tokens",""),IF(M19="","Missing QA multiplier",""),IF(T19="","Missing assumption notes","")))
A20: CRM Data Enrichment | B20: Account monitoring | C20: Weekly batch | D20: 2000 | E20: Weekly | F20: {=IFERROR(XLOOKUP(E20,'Cadence Reference'!$A$5:$A$12,'Cadence Reference'!$B$5:$B$12),"")} -> 52 | G20: 2000 | H20: 150 | I20: GPT-5.4 mini | J20: {=IFERROR(XLOOKUP(I20,'Pricing Reference'!$B$5:$B$12,'Pricing Reference'!$D$5:$D$12),"")} -> 0.75 | K20: {=IFERROR(XLOOKUP(I20,'Pricing Reference'!$B$5:$B$12,'Pricing Reference'!$E$5:$E$12),"")} -> 4.5 | L20: 0.05 | M20: 1 | N20: =IF(OR(G20="",I20=""),"",((G20*J20)+(H20*K20))/1000000) -> 0.002175 | O20: =IF(N20="","",N20*(1+L20)*M20) -> 0.00228375 | P20: =IF(OR(D20="",O20=""),"",D20*O20) -> 4.5675 | Q20: =IF(OR(P20="",F20=""),"",P20*F20) -> 237.51 | S20: =IF(R20="","",IF(O20=0,"",R20/O20-1)) | T20: Extracts key entities from notes to enrich CRM fields. | V20: =IF(A20="","",TEXTJOIN("; ",TRUE,IF(B20="","Missing operating area",""),IF(E20="","Missing cadence",""),IF(I20="","Missing model",""),IF(D20="","Missing volume",""),IF(G20="","Missing input tokens",""),IF(M20="","Missing QA multiplier",""),IF(T20="","Missing assumption notes","")))
A21: Sales Pipeline RAG Indexing | B21: Prioritization | C21: Daily sync | D21: 5000 | E21: Business day | F21: {=IFERROR(XLOOKUP(E21,'Cadence Reference'!$A$5:$A$12,'Cadence Reference'!$B$5:$B$12),"")} -> 260 | G21: 1000 | H21: 0 | I21: text-embedding-3-small | J21: {=IFERROR(XLOOKUP(I21,'Pricing Reference'!$B$5:$B$12,'Pricing Reference'!$D$5:$D$12),"")} -> 0.02 | K21: {=IFERROR(XLOOKUP(I21,'Pricing Reference'!$B$5:$B$12,'Pricing Reference'!$E$5:$E$12),"")} -> 0 | L21: 0.02 | M21: 1 | N21: =IF(OR(G21="",I21=""),"",((G21*J21)+(H21*K21))/1000000) -> 2e-05 | O21: =IF(N21="","",N21*(1+L21)*M21) -> 2.04e-05 | P21: =IF(OR(D21="",O21=""),"",D21*O21) -> 0.102 | Q21: =IF(OR(P21="",F21=""),"",P21*F21) -> 26.52 | S21: =IF(R21="","",IF(O21=0,"",R21/O21-1)) | T21: Embeds sales notes for semantic search. | V21: =IF(A21="","",TEXTJOIN("; ",TRUE,IF(B21="","Missing operating area",""),IF(E21="","Missing cadence",""),IF(I21="","Missing model",""),IF(D21="","Missing volume",""),IF(G21="","Missing input tokens",""),IF(M21="","Missing QA multiplier",""),IF(T21="","Missing assumption notes","")))
F22: {=IFERROR(XLOOKUP(E22,'Cadence Reference'!$A$5:$A$12,'Cadence Reference'!$B$5:$B$12),"")} | J22: {=IFERROR(XLOOKUP(I22,'Pricing Reference'!$B$5:$B$12,'Pricing Reference'!$D$5:$D$12),"")} | K22: {=IFERROR(XLOOKUP(I22,'Pricing Reference'!$B$5:$B$12,'Pricing Reference'!$E$5:$E$12),"")} | N22: =IF(OR(G22="",I22=""),"",((G22*J22)+(H22*K22))/1000000) | O22: =IF(N22="","",N22*(1+L22)*M22) | P22: =IF(OR(D22="",O22=""),"",D22*O22) | Q22: =IF(OR(P22="",F22=""),"",P22*F22) | S22: =IF(R22="","",IF(O22=0,"",R22/O22-1)) | V22: =IF(A22="","",TEXTJOIN("; ",TRUE,IF(B22="","Missing operating area",""),IF(E22="","Missing cadence",""),IF(I22="","Missing model",""),IF(D22="","Missing volume",""),IF(G22="","Missing input tokens",""),IF(M22="","Missing QA multiplier",""),IF(T22="","Missing assumption notes","")))
F23: {=IFERROR(XLOOKUP(E23,'Cadence Reference'!$A$5:$A$12,'Cadence Reference'!$B$5:$B$12),"")} | J23: {=IFERROR(XLOOKUP(I23,'Pricing Reference'!$B$5:$B$12,'Pricing Reference'!$D$5:$D$12),"")} | K23: {=IFERROR(XLOOKUP(I23,'Pricing Reference'!$B$5:$B$12,'Pricing Reference'!$E$5:$E$12),"")} | N23: =IF(OR(G23="",I23=""),"",((G23*J23)+(H23*K23))/1000000) | O23: =IF(N23="","",N23*(1+L23)*M23) | P23: =IF(OR(D23="",O23=""),"",D23*O23) | Q23: =IF(OR(P23="",F23=""),"",P23*F23) | S23: =IF(R23="","",IF(O23=0,"",R23/O23-1)) | V23: =IF(A23="","",TEXTJOIN("; ",TRUE,IF(B23="","Missing operating area",""),IF(E23="","Missing cadence",""),IF(I23="","Missing model",""),IF(D23="","Missing volume",""),IF(G23="","Missing input tokens",""),IF(M23="","Missing QA multiplier",""),IF(T23="","Missing assumption notes","")))
F24: {=IFERROR(XLOOKUP(E24,'Cadence Reference'!$A$5:$A$12,'Cadence Reference'!$B$5:$B$12),"")} | J24: {=IFERROR(XLOOKUP(I24,'Pricing Reference'!$B$5:$B$12,'Pricing Reference'!$D$5:$D$12),"")} | K24: {=IFERROR(XLOOKUP(I24,'Pricing Reference'!$B$5:$B$12,'Pricing Reference'!$E$5:$E$12),"")} | N24: =IF(OR(G24="",I24=""),"",((G24*J24)+(H24*K24))/1000000) | O24: =IF(N24="","",N24*(1+L24)*M24) | P24: =IF(OR(D24="",O24=""),"",D24*O24) | Q24: =IF(OR(P24="",F24=""),"",P24*F24) | S24: =IF(R24="","",IF(O24=0,"",R24/O24-1)) | V24: =IF(A24="","",TEXTJOIN("; ",TRUE,IF(B24="","Missing operating area",""),IF(E24="","Missing cadence",""),IF(I24="","Missing model",""),IF(D24="","Missing volume",""),IF(G24="","Missing input tokens",""),IF(M24="","Missing QA multiplier",""),IF(T24="","Missing assumption notes","")))
F25: {=IFERROR(XLOOKUP(E25,'Cadence Reference'!$A$5:$A$12,'Cadence Reference'!$B$5:$B$12),"")} | J25: {=IFERROR(XLOOKUP(I25,'Pricing Reference'!$B$5:$B$12,'Pricing Reference'!$D$5:$D$12),"")} | K25: {=IFERROR(XLOOKUP(I25,'Pricing Reference'!$B$5:$B$12,'Pricing Reference'!$E$5:$E$12),"")} | N25: =IF(OR(G25="",I25=""),"",((G25*J25)+(H25*K25))/1000000) | O25: =IF(N25="","",N25*(1+L25)*M25) | P25: =IF(OR(D25="",O25=""),"",D25*O25) | Q25: =IF(OR(P25="",F25=""),"",P25*F25) | S25: =IF(R25="","",IF(O25=0,"",R25/O25-1)) | V25: =IF(A25="","",TEXTJOIN("; ",TRUE,IF(B25="","Missing operating area",""),IF(E25="","Missing cadence",""),IF(I25="","Missing model",""),IF(D25="","Missing volume",""),IF(G25="","Missing input tokens",""),IF(M25="","Missing QA multiplier",""),IF(T25="","Missing assumption notes","")))
F26: {=IFERROR(XLOOKUP(E26,'Cadence Reference'!$A$5:$A$12,'Cadence Reference'!$B$5:$B$12),"")} | J26: {=IFERROR(XLOOKUP(I26,'Pricing Reference'!$B$5:$B$12,'Pricing Reference'!$D$5:$D$12),"")} | K26: {=IFERROR(XLOOKUP(I26,'Pricing Reference'!$B$5:$B$12,'Pricing Reference'!$E$5:$E$12),"")} | N26: =IF(OR(G26="",I26=""),"",((G26*J26)+(H26*K26))/1000000) | O26: =IF(N26="","",N26*(1+L26)*M26) | P26: =IF(OR(D26="",O26=""),"",D26*O26) | Q26: =IF(OR(P26="",F26=""),"",P26*F26) | S26: =IF(R26="","",IF(O26=0,"",R26/O26-1)) | V26: =IF(A26="","",TEXTJOIN("; ",TRUE,IF(B26="","Missing operating area",""),IF(E26="","Missing cadence",""),IF(I26="","Missing model",""),IF(D26="","Missing volume",""),IF(G26="","Missing input tokens",""),IF(M26="","Missing QA multiplier",""),IF(T26="","Missing assumption notes","")))
F27: {=IFERROR(XLOOKUP(E27,'Cadence Reference'!$A$5:$A$12,'Cadence Reference'!$B$5:$B$12),"")} | J27: {=IFERROR(XLOOKUP(I27,'Pricing Reference'!$B$5:$B$12,'Pricing Reference'!$D$5:$D$12),"")} | K27: {=IFERROR(XLOOKUP(I27,'Pricing Reference'!$B$5:$B$12,'Pricing Reference'!$E$5:$E$12),"")} | N27: =IF(OR(G27="",I27=""),"",((G27*J27)+(H27*K27))/1000000) | O27: =IF(N27="","",N27*(1+L27)*M27) | P27: =IF(OR(D27="",O27=""),"",D27*O27) | Q27: =IF(OR(P27="",F27=""),"",P27*F27) | S27: =IF(R27="","",IF(O27=0,"",R27/O27-1)) | V27: =IF(A27="","",TEXTJOIN("; ",TRUE,IF(B27="","Missing operating area",""),IF(E27="","Missing cadence",""),IF(I27="","Missing model",""),IF(D27="","Missing volume",""),IF(G27="","Missing input tokens",""),IF(M27="","Missing QA multiplier",""),IF(T27="","Missing assumption notes","")))
F28: {=IFERROR(XLOOKUP(E28,'Cadence Reference'!$A$5:$A$12,'Cadence Reference'!$B$5:$B$12),"")} | J28: {=IFERROR(XLOOKUP(I28,'Pricing Reference'!$B$5:$B$12,'Pricing Reference'!$D$5:$D$12),"")} | K28: {=IFERROR(XLOOKUP(I28,'Pricing Reference'!$B$5:$B$12,'Pricing Reference'!$E$5:$E$12),"")} | N28: =IF(OR(G28="",I28=""),"",((G28*J28)+(H28*K28))/1000000) | O28: =IF(N28="","",N28*(1+L28)*M28) | P28: =IF(OR(D28="",O28=""),"",D28*O28) | Q28: =IF(OR(P28="",F28=""),"",P28*F28) | S28: =IF(R28="","",IF(O28=0,"",R28/O28-1)) | V28: =IF(A28="","",TEXTJOIN("; ",TRUE,IF(B28="","Missing operating area",""),IF(E28="","Missing cadence",""),IF(I28="","Missing model",""),IF(D28="","Missing volume",""),IF(G28="","Missing input tokens",""),IF(M28="","Missing QA multiplier",""),IF(T28="","Missing assumption notes","")))
F29: {=IFERROR(XLOOKUP(E29,'Cadence Reference'!$A$5:$A$12,'Cadence Reference'!$B$5:$B$12),"")} | J29: {=IFERROR(XLOOKUP(I29,'Pricing Reference'!$B$5:$B$12,'Pricing Reference'!$D$5:$D$12),"")} | K29: {=IFERROR(XLOOKUP(I29,'Pricing Reference'!$B$5:$B$12,'Pricing Reference'!$E$5:$E$12),"")} | N29: =IF(OR(G29="",I29=""),"",((G29*J29)+(H29*K29))/1000000) | O29: =IF(N29="","",N29*(1+L29)*M29) | P29: =IF(OR(D29="",O29=""),"",D29*O29) | Q29: =IF(OR(P29="",F29=""),"",P29*F29) | S29: =IF(R29="","",IF(O29=0,"",R29/O29-1)) | V29: =IF(A29="","",TEXTJOIN("; ",TRUE,IF(B29="","Missing operating area",""),IF(E29="","Missing cadence",""),IF(I29="","Missing model",""),IF(D29="","Missing volume",""),IF(G29="","Missing input tokens",""),IF(M29="","Missing QA multiplier",""),IF(T29="","Missing assumption notes","")))
F30: {=IFERROR(XLOOKUP(E30,'Cadence Reference'!$A$5:$A$12,'Cadence Reference'!$B$5:$B$12),"")} | J30: {=IFERROR(XLOOKUP(I30,'Pricing Reference'!$B$5:$B$12,'Pricing Reference'!$D$5:$D$12),"")} | K30: {=IFERROR(XLOOKUP(I30,'Pricing Reference'!$B$5:$B$12,'Pricing Reference'!$E$5:$E$12),"")} | N30: =IF(OR(G30="",I30=""),"",((G30*J30)+(H30*K30))/1000000) | O30: =IF(N30="","",N30*(1+L30)*M30) | P30: =IF(OR(D30="",O30=""),"",D30*O30) | Q30: =IF(OR(P30="",F30=""),"",P30*F30) | S30: =IF(R30="","",IF(O30=0,"",R30/O30-1)) | V30: =IF(A30="","",TEXTJOIN("; ",TRUE,IF(B30="","Missing operating area",""),IF(E30="","Missing cadence",""),IF(I30="","Missing model",""),IF(D30="","Missing volume",""),IF(G30="","Missing input tokens",""),IF(M30="","Missing QA multiplier",""),IF(T30="","Missing assumption notes","")))
F31: {=IFERROR(XLOOKUP(E31,'Cadence Reference'!$A$5:$A$12,'Cadence Reference'!$B$5:$B$12),"")} | J31: {=IFERROR(XLOOKUP(I31,'Pricing Reference'!$B$5:$B$12,'Pricing Reference'!$D$5:$D$12),"")} | K31: {=IFERROR(XLOOKUP(I31,'Pricing Reference'!$B$5:$B$12,'Pricing Reference'!$E$5:$E$12),"")} | N31: =IF(OR(G31="",I31=""),"",((G31*J31)+(H31*K31))/1000000) | O31: =IF(N31="","",N31*(1+L31)*M31) | P31: =IF(OR(D31="",O31=""),"",D31*O31) | Q31: =IF(OR(P31="",F31=""),"",P31*F31) | S31: =IF(R31="","",IF(O31=0,"",R31/O31-1)) | V31: =IF(A31="","",TEXTJOIN("; ",TRUE,IF(B31="","Missing operating area",""),IF(E31="","Missing cadence",""),IF(I31="","Missing model",""),IF(D31="","Missing volume",""),IF(G31="","Missing input tokens",""),IF(M31="","Missing QA multiplier",""),IF(T31="","Missing assumption notes","")))
F32: {=IFERROR(XLOOKUP(E32,'Cadence Reference'!$A$5:$A$12,'Cadence Reference'!$B$5:$B$12),"")} | J32: {=IFERROR(XLOOKUP(I32,'Pricing Reference'!$B$5:$B$12,'Pricing Reference'!$D$5:$D$12),"")} | K32: {=IFERROR(XLOOKUP(I32,'Pricing Reference'!$B$5:$B$12,'Pricing Reference'!$E$5:$E$12),"")} | N32: =IF(OR(G32="",I32=""),"",((G32*J32)+(H32*K32))/1000000) | O32: =IF(N32="","",N32*(1+L32)*M32) | P32: =IF(OR(D32="",O32=""),"",D32*O32) | Q32: =IF(OR(P32="",F32=""),"",P32*F32) | S32: =IF(R32="","",IF(O32=0,"",R32/O32-1)) | V32: =IF(A32="","",TEXTJOIN("; ",TRUE,IF(B32="","Missing operating area",""),IF(E32="","Missing cadence",""),IF(I32="","Missing model",""),IF(D32="","Missing volume",""),IF(G32="","Missing input tokens",""),IF(M32="","Missing QA multiplier",""),IF(T32="","Missing assumption notes","")))
F33: {=IFERROR(XLOOKUP(E33,'Cadence Reference'!$A$5:$A$12,'Cadence Reference'!$B$5:$B$12),"")} | J33: {=IFERROR(XLOOKUP(I33,'Pricing Reference'!$B$5:$B$12,'Pricing Reference'!$D$5:$D$12),"")} | K33: {=IFERROR(XLOOKUP(I33,'Pricing Reference'!$B$5:$B$12,'Pricing Reference'!$E$5:$E$12),"")} | N33: =IF(OR(G33="",I33=""),"",((G33*J33)+(H33*K33))/1000000) | O33: =IF(N33="","",N33*(1+L33)*M33) | P33: =IF(OR(D33="",O33=""),"",D33*O33) | Q33: =IF(OR(P33="",F33=""),"",P33*F33) | S33: =IF(R33="","",IF(O33=0,"",R33/O33-1)) | V33: =IF(A33="","",TEXTJOIN("; ",TRUE,IF(B33="","Missing operating area",""),IF(E33="","Missing cadence",""),IF(I33="","Missing model",""),IF(D33="","Missing volume",""),IF(G33="","Missing input tokens",""),IF(M33="","Missing QA multiplier",""),IF(T33="","Missing assumption notes","")))
... F62: {=IFERROR(XLOOKUP(E62,'Cadence Reference'!$A$5:$A$12,'Cadence Reference'!$B$5:$B$12),"")} | J62: {=IFERROR(XLOOKUP(I62,'Pricing Reference'!$B$5:$B$12,'Pricing Reference'!$D$5:$D$12),"")} | K62: {=IFERROR(XLOOKUP(I62,'Pricing Reference'!$B$5:$B$12,'Pricing Reference'!$E$5:$E$12),"")} | N62: =IF(OR(G62="",I62=""),"",((G62*J62)+(H62*K62))/1000000) | O62: =IF(N62="","",N62*(1+L62)*M62) | P62: =IF(OR(D62="",O62=""),"",D62*O62) | Q62: =IF(OR(P62="",F62=""),"",P62*F62) | S62: =IF(R62="","",IF(O62=0,"",R62/O62-1)) | V62: =IF(A62="","",TEXTJOIN("; ",TRUE,IF(B62="","Missing operating area",""),IF(E62="","Missing cadence",""),IF(I62="","Missing model",""),IF(D62="","Missing volume",""),IF(G62="","Missing input tokens",""),IF(M62="","Missing QA multiplier",""),IF(T62="","Missing assumption notes","")))

Sheet Scenario Analysis
A1: Scenario Analysis
A2: Use this to test sensitivity. Fill multipliers for Base, Scaled, Stress, and Optimized cases. Explain each scenario in the rationale column.
A4: Scenario | B4: Volume multiplier | C4: Token-size multiplier | D4: Model price multiplier | E4: QA/retry multiplier | F4: Estimated annual cost | G4: Budget utilization | H4: Rationale
A5: Base case | B5: 1 | C5: 1 | D5: 1 | E5: 1 | F5: =IF(COUNTA(B5:E5)<4,"",'Token Math Template'!$B$4*B5*C5*D5*E5) -> 8280.0073 | G5: =IF(F5="","",F5/'Token Math Template'!$B$3) -> 0.16560015 | H5: Expected production usage based on your Token Math Template.
A6: Scaled case | B6: 3 | C6: 1.5 | D6: 1 | E6: 1 | F6: =IF(COUNTA(B6:E6)<4,"",'Token Math Template'!$B$4*B6*C6*D6*E6) -> 37260.033 | G6: =IF(F6="","",F6/'Token Math Template'!$B$3) -> 0.74520065 | H6: Rapid customer growth leading to 3x volume and longer contexts.
A7: Stress case | B7: 5 | C7: 2 | D7: 1.2 | E7: 1.5 | F7: =IF(COUNTA(B7:E7)<4,"",'Token Math Template'!$B$4*B7*C7*D7*E7) -> 149040.13 | G7: =IF(F7="","",F7/'Token Math Template'!$B$3) -> 2.9808026 | H7: Major spike in support tickets and complex escalations; increased retry rates.
A8: Optimized case | B8: 1 | C8: 0.8 | D8: 0.5 | E8: 0.9 | F8: =IF(COUNTA(B8:E8)<4,"",'Token Math Template'!$B$4*B8*C8*D8*E8) -> 2980.8026 | G8: =IF(F8="","",F8/'Token Math Template'!$B$3) -> 0.059616052 | H8: Implementation of prompt caching, batching, and strict token limits.

Sheet Candidate Assumptions
A1: Category | B1: Rationale
A2: Volume & Cadence | B2: Volume assumptions are based on a mid-sized B2B Sales CRM processing ~500 leads/day, 2000 support emails, and ~300 meetings. Cadence factors are set to 260 for business-day operations and 365 for calendar-day operations like support.
A3: Model Routing | B3: We route high-volume triage and data extraction to cost-effective models (Claude Haiku 4.5, GPT-5.4 mini) and reserve frontier models (Claude Opus 4.7, GPT-5.5) exclusively for complex deal escalations and quality assurance.
A4: Context Size & Retries | B4: Input context sizes range from 1,000 tokens for basic triage to 15,000 tokens for deep deal analysis. Retry rates (5-15%) and QA multipliers (1.0x-1.2x) are applied based on task complexity and risk.
A5: Budget Utilization | B5: The current design is highly efficient, utilizing a small portion of the $50,000 budget. This leaves significant headroom for scaling, adding more complex agents, or handling unexpected spikes in volume.
